neufbox/__init__.py
neufbox/auth.py
neufbox/client.py
neufbox/namespaces/__init__.py
neufbox/namespaces/_base.py
neufbox/namespaces/auth.py
neufbox/namespaces/backup3g.py
neufbox/namespaces/ddns.py
neufbox/namespaces/dsl.py
neufbox/namespaces/firewall.py
neufbox/namespaces/ftth.py
neufbox/namespaces/guest.py
neufbox/namespaces/hotspot.py
neufbox/namespaces/lan.py
neufbox/namespaces/ont.py
neufbox/namespaces/p910nd.py
neufbox/namespaces/ppp.py
neufbox/namespaces/smb.py
neufbox/namespaces/system.py
neufbox/namespaces/tv.py
neufbox/namespaces/usb.py
neufbox/namespaces/voip.py
neufbox/namespaces/wan.py
neufbox/namespaces/wlan.py
neufbox/namespaces/wlan5.py
neufbox_client-1.0.0.dist-info/LICENSE
neufbox_client-1.0.0.dist-info/METADATA
neufbox_client-1.0.0.dist-info/WHEEL
neufbox_client-1.0.0.dist-info/top_level.txt
neufbox_client-1.0.0.dist-info/RECORD
