Metadata-Version: 2.1
Name: neufbox-client
Version: 1.0.0
Summary: Neufbox API Client
Home-page: https://github.com/sprat/neufbox-client
Author: Sylvain Prat
Author-email: sylvain.prat+neufbox-client@gmail.com
License: MIT License
Download-URL: https://pypi.python.org/pypi/neufbox-client
Keywords: neuf,sfr,redbysfr,box,api,client
Platform: any
Classifier: Development Status :: 5 - Production/Stable
Classifier: Intended Audience :: Developers
Classifier: Intended Audience :: Information Technology
Classifier: License :: OSI Approved :: MIT License
Classifier: Operating System :: OS Independent
Classifier: Programming Language :: Python :: 3 :: Only
Classifier: Topic :: System :: Networking
Classifier: Topic :: Software Development :: Libraries :: Python Modules
Classifier: Topic :: Software Development :: Libraries :: Application Frameworks
Requires-Python: >=3.6
Requires-Dist: requests
Requires-Dist: xmltodict
Provides-Extra: test
Requires-Dist: pytest ; extra == 'test'
Requires-Dist: pytest-cov ; extra == 'test'
Requires-Dist: pytest-pylint ; extra == 'test'
Requires-Dist: python-dotenv ; extra == 'test'
Requires-Dist: requests-mock ; extra == 'test'
